repl_chat/__init__.py
repl_chat/chat.py
repl_chat/dspy_chat.py
agent_repl_chat-0.2.0.dist-info/METADATA
agent_repl_chat-0.2.0.dist-info/WHEEL
agent_repl_chat-0.2.0.dist-info/licenses/LICENSE
agent_repl_chat-0.2.0.dist-info/RECORD
