Metadata-Version: 2.4
Name: agent-repl-chat
Version: 0.2.0
Summary: A beautiful terminal chat interface for OpenAI agents and DSPy Modules
Author-email: Facundo Goiriz <facundogoiriz@gmail.com>
License: MIT
License-File: LICENSE
Keywords: agents,chat,cli,dspy,openai,repl,terminal
Classifier: Development Status :: 4 - Beta
Classifier: Environment :: Console
Classifier: Intended Audience :: Developers
Classifier: License :: OSI Approved :: MIT License
Classifier: Programming Language :: Python :: 3
Classifier: Programming Language :: Python :: 3.11
Classifier: Programming Language :: Python :: 3.12
Classifier: Topic :: Communications :: Chat
Classifier: Topic :: Software Development :: Libraries :: Python Modules
Requires-Python: >=3.11
Requires-Dist: dspy>=2.6.27
Requires-Dist: openai-agents
Requires-Dist: prompt-toolkit
Requires-Dist: rich
